pathsim_chem/.DS_Store
pathsim_chem/__init__.py
pathsim_chem/_version.py
pathsim_chem/tritium/.DS_Store
pathsim_chem/tritium/README.md
pathsim_chem/tritium/__init__.py
pathsim_chem/tritium/bubbler.py
pathsim_chem/tritium/residencetime.py
pathsim_chem/tritium/splitter.py
pathsim_chem/tritium/tcap.py
pathsim_chem-0.1.0.dist-info/licenses/LICENSE
pathsim_chem-0.1.0.dist-info/METADATA
pathsim_chem-0.1.0.dist-info/WHEEL
pathsim_chem-0.1.0.dist-info/top_level.txt
pathsim_chem-0.1.0.dist-info/RECORD
