Metadata-Version: 2.4
Name: pathsim-chem
Version: 0.1.0
Summary: Chemical Engineering Blocks for PathSim
Author: PathSim Contributors
License: MIT
Project-URL: Homepage, https://github.com/pathsim/pathsim-chem
Project-URL: Documentation, https://pathsim-chem.readthedocs.io
Project-URL: Repository, https://github.com/pathsim/pathsim-chem
Project-URL: Issues, https://github.com/pathsim/pathsim-chem/issues
Keywords: simulation,chemical engineering,process modeling
Classifier: Development Status :: 3 - Alpha
Classifier: Intended Audience :: Science/Research
Classifier: License :: OSI Approved :: MIT License
Classifier: Programming Language :: Python :: 3
Classifier: Programming Language :: Python :: 3.9
Classifier: Programming Language :: Python :: 3.10
Classifier: Programming Language :: Python :: 3.11
Classifier: Programming Language :: Python :: 3.12
Classifier: Programming Language :: Python :: 3.13
Classifier: Topic :: Scientific/Engineering
Requires-Python: >=3.9
License-File: LICENSE
Requires-Dist: pathsim
Requires-Dist: numpy<2,>=1.15
Requires-Dist: scipy>=1.2
Provides-Extra: test
Requires-Dist: pytest>=7.0; extra == "test"
Requires-Dist: pytest-cov>=4.0; extra == "test"
Provides-Extra: docs
Requires-Dist: sphinx>=7.0; extra == "docs"
Requires-Dist: furo; extra == "docs"
Requires-Dist: myst-parser; extra == "docs"
Requires-Dist: sphinx-copybutton; extra == "docs"
Requires-Dist: sphinx-design; extra == "docs"
Dynamic: license-file
